aldryn_boilerplates/__init__.py
aldryn_boilerplates/apps.py
aldryn_boilerplates/conf.py
aldryn_boilerplates/context_processors.py
aldryn_boilerplates/models.py
aldryn_boilerplates/staticfile_finders.py
aldryn_boilerplates/template_loaders.py
aldryn_boilerplates/tests.py
aldryn_boilerplates/test_helpers/__init__.py
aldryn_boilerplates/test_helpers/testapp/__init__.py
aldryn_boilerplates/test_helpers/testapp/models.py
aldryn_boilerplates/test_helpers/testapp/boilerplates/other-test-boilerplate/templates/test.html
aldryn_boilerplates/test_helpers/testapp/boilerplates/test-boilerplate/static/test-only-in-boilerplate.txt
aldryn_boilerplates/test_helpers/testapp/boilerplates/test-boilerplate/static/test.txt
aldryn_boilerplates/test_helpers/testapp/boilerplates/test-boilerplate/templates/test-only-in-boilerplate.html
aldryn_boilerplates/test_helpers/testapp/boilerplates/test-boilerplate/templates/test.html
aldryn_boilerplates/test_helpers/testapp/static/test-only-in-static.txt
aldryn_boilerplates/test_helpers/testapp/static/test.txt
aldryn_boilerplates/test_helpers/testapp/templates/test-only-in-templates.html
aldryn_boilerplates/test_helpers/testapp/templates/test.html
aldryn_boilerplates/test_helpers/testapp_no_default/__init__.py
aldryn_boilerplates/test_helpers/testapp_no_default/models.py
aldryn_boilerplates/test_helpers/testapp_no_default/boilerplates/test-boilerplate/static/no_default_static_folder_app.txt
aldryn_boilerplates/test_helpers/testapp_no_default/boilerplates/test-boilerplate/templates/no_default_templates_folder_app.html
aldryn_boilerplates-0.7.7.dist-info/DESCRIPTION.rst
aldryn_boilerplates-0.7.7.dist-info/METADATA
aldryn_boilerplates-0.7.7.dist-info/RECORD
aldryn_boilerplates-0.7.7.dist-info/WHEEL
aldryn_boilerplates-0.7.7.dist-info/metadata.json
aldryn_boilerplates-0.7.7.dist-info/top_level.txt
