Metadata-Version: 1.1
Name: aldryn-boilerplates
Version: 0.7.7
Summary: An extension that allows re-usable apps to provide sets of templates and staticfiles for different boilerplates.
Home-page: https://github.com/aldryn/aldryn-boilerplates/
Author: Stefan Foulis
Author-email: stefan@foulis.ch
License: BSD
Platform: OS Independent
Classifier: Development Status :: 4 - Beta
Classifier: Framework :: Django
Classifier: Intended Audience :: Developers
Classifier: License :: OSI Approved :: BSD License
Classifier: Operating System :: OS Independent
Classifier: Programming Language :: Python
Classifier: Topic :: Internet :: WWW/HTTP
Classifier: Programming Language :: Python :: 2.6
Classifier: Programming Language :: Python :: 2.7
